<japan-tree.xml>
  <settings>	normal	</settings>
  <grid>	grid_1	  <rows>	10	</rows>
    <columns>	10	</columns>
  </grid>
  <nodes>
    <NC27>
      <row>	1	</row>
      <column>	1	</column>
      <lines>
        <Ha_Go></Ha_Go>
        <Chi_Ni></Chi_Ni>
      </lines>
    </NC27>
    <Ha_Go>
      <row>	5	</row>
      <column>	2	</column>
      <lines>
        <Ke_Ni></Ke_Ni>
      </lines>
    </Ha_Go>
    <Chi_Ni>
      <row>	6	</row>
      <column>	2	</column>
      <lines>
        <Chi_Ha></Chi_Ha>
      </lines>
    </Chi_Ni>
    <Te_Ke>
      <row>	7	</row>
      <column>	2	</column>
    </Te_Ke>
    <Ke_Ni>
      <row>	5	</row>
      <column>	3	</column>
      <lines>
        <Ke_Ho></Ke_Ho>
      </lines>
    </Ke_Ni>
    <Chi_Ha>
      <row>	6	</row>
      <column>	3	</column>
      <lines>
        <Chi_He></Chi_He>
      </lines>
    </Chi_Ha>
    <Ke_Ni_B>
      <row>	7	</row>
      <column>	3	</column>
    </Ke_Ni_B>
    <Ke_Ho>
      <row>	5	</row>
      <column>	4	</column>
      <lines>
        <Chi_Nu>
          <line>	H_Diag	</line>
        </Chi_Nu>
      </lines>
    </Ke_Ho>
    <Chi_He>
      <row>	6	</row>
      <column>	4	</column>
      <lines>
        <Chi_Nu></Chi_Nu>
      </lines>
    </Chi_He>
    <Chi_Nu>
      <row>	6	</row>
      <column>	5	</column>
      <lines>
        <Chi_To></Chi_To>
      </lines>
    </Chi_Nu>
    <Chi_Nu_Kai>
      <row>	7	</row>
      <column>	5	</column>
    </Chi_Nu_Kai>
    <Chi_To>
      <row>	6	</row>
      <column>	6	</column>
      <lines>
        <Chi_Ri></Chi_Ri>
      </lines>
    </Chi_To>
    <Chi_Ri>
      <row>	6	</row>
      <column>	7	</column>
      <lines>
        <STA_1></STA_1>
      </lines>
    </Chi_Ri>
    <STA_1>
      <row>	6	</row>
      <column>	8	</column>
      <lines>
        <Type_61></Type_61>
      </lines>
    </STA_1>
    <J18_STA_2_3>
      <row>	7	</row>
      <column>	8	</column>
    </J18_STA_2_3>
    <Type_61>
      <row>	6	</row>
      <column>	9	</column>
      <lines>
        <ST_B1></ST_B1>
      </lines>
    </Type_61>
    <ST_B1>
      <row>	6	</row>
      <column>	10	</column>
    </ST_B1>
  </nodes>
</japan-tree.xml>
